odoo10_addon_l10n_ch_bank-10.0.1.0.1-py2.7-nspkg.pth
odoo/addons/l10n_ch_bank/README.rst
odoo/addons/l10n_ch_bank/__init__.py
odoo/addons/l10n_ch_bank/__manifest__.py
odoo/addons/l10n_ch_bank/data/res.bank.csv
odoo/addons/l10n_ch_bank/i18n/de.po
odoo/addons/l10n_ch_bank/i18n/fr.po
odoo/addons/l10n_ch_bank/i18n/it.po
odoo/addons/l10n_ch_bank/i18n/nb_NO.po
odoo/addons/l10n_ch_bank/migrations/8.0.9.0.0/pre-migration.py
odoo/addons/l10n_ch_bank/migrations/9.0.9.0.0/pre-migration.py
odoo/addons/l10n_ch_bank/models/__init__.py
odoo/addons/l10n_ch_bank/models/bank.py
odoo/addons/l10n_ch_bank/static/description/icon.png
odoo10_addon_l10n_ch_bank-10.0.1.0.1.dist-info/DESCRIPTION.rst
odoo10_addon_l10n_ch_bank-10.0.1.0.1.dist-info/METADATA
odoo10_addon_l10n_ch_bank-10.0.1.0.1.dist-info/RECORD
odoo10_addon_l10n_ch_bank-10.0.1.0.1.dist-info/WHEEL
odoo10_addon_l10n_ch_bank-10.0.1.0.1.dist-info/metadata.json
odoo10_addon_l10n_ch_bank-10.0.1.0.1.dist-info/namespace_packages.txt
odoo10_addon_l10n_ch_bank-10.0.1.0.1.dist-info/top_level.txt
